LICENSE
MANIFEST.in
README.md
requirements.txt
setup.py
lib_pygame_ui.egg-info/PKG-INFO
lib_pygame_ui.egg-info/SOURCES.txt
lib_pygame_ui.egg-info/dependency_links.txt
lib_pygame_ui.egg-info/requires.txt
lib_pygame_ui.egg-info/top_level.txt
libpygameui/__init__.py
libpygameui/button.py
libpygameui/manager.py
libpygameui/scroller.py
libpygameui/wrap.py
libpygameui/_utils/__init__.py
libpygameui/_utils/constants.py
libpygameui/_utils/decorators.py
libpygameui/_utils/events.py
libpygameui/_utils/tools.py
libpygameui/_utils/unions.py